pytorch_histogram_matching/__init__.py
pytorch_histogram_matching-0.0.6.dist-info/LICENSE
pytorch_histogram_matching-0.0.6.dist-info/METADATA
pytorch_histogram_matching-0.0.6.dist-info/WHEEL
pytorch_histogram_matching-0.0.6.dist-info/top_level.txt
pytorch_histogram_matching-0.0.6.dist-info/RECORD
