Metadata-Version: 2.1
Name: pytorch-histogram-matching
Version: 0.0.6
Summary: pytorch implementation of histogram matching
Home-page: https://github.com/nemodleo/pytorch-histogram-matching
Author: Hyun Park
Author-email: nemod.leo@snu.ac.kr
License: MIT
Keywords: hm color pytorch histogram matching
Platform: UNKNOWN
Classifier: License :: OSI Approved :: MIT License
Requires-Python: >= 3.6
